remolib.py
remolib-0.0.1.dist-info/WHEEL
remolib-0.0.1.dist-info/METADATA
remolib-0.0.1.dist-info/RECORD
